{
  "$schema": "../node_modules/@tauri-apps/cli/config.schema.json",
  "productName": "QuickPaste",
  "version": "0.9.0",
  "identifier": "com.quickpaste.desktop",
  "build": {
    "frontendDist": "../dist",
    "devUrl": "http://127.0.0.1:4173",
    "beforeDevCommand": "npm run dev -- --host 127.0.0.1 --port 4173",
    "beforeBuildCommand": "npm run build"
  },
  "app": {
    "windows": [
      {
        "title": "闪电剪贴板 QuickPaste",
        "width": 800,
        "height": 580,
        "center": false,
        "visible": false,
        "decorations": false,
        "transparent": true,
        "backgroundColor": "#00000000",
        "shadow": false,
        "resizable": false,
        "alwaysOnTop": true,
        "skipTaskbar": true,
        "fullscreen": false
      }
    ],
    "security": {
      "csp": "default-src 'self'; connect-src ipc: http://ipc.localhost; img-src 'self' asset: http://asset.localhost data:; style-src 'self' 'unsafe-inline'; font-src 'self'"
    }
  },
  "bundle": {
    "active": true,
    "targets": ["nsis"],
    "resources": {
      "../THIRD_PARTY_NOTICES.md": "THIRD_PARTY_NOTICES.md",
      "../THIRD_PARTY_LICENSES_NPM.md": "THIRD_PARTY_LICENSES_NPM.md",
      "../THIRD_PARTY_LICENSES_RUST.md": "THIRD_PARTY_LICENSES_RUST.md",
      "../THIRD_PARTY_LICENSES_NATIVE.md": "THIRD_PARTY_LICENSES_NATIVE.md"
    },
    "publisher": "QuickPaste",
    "icon": [
      "icons/32x32.png",
      "icons/128x128.png",
      "icons/128x128@2x.png",
      "icons/icon.ico"
    ],
    "windows": {
      "allowDowngrades": false,
      "webviewInstallMode": {
        "type": "downloadBootstrapper",
        "silent": true
      },
      "nsis": {
        "installMode": "currentUser",
        "languages": ["SimpChinese", "English"],
        "displayLanguageSelector": false,
        "compression": "lzma",
        "startMenuFolder": "QuickPaste"
      }
    }
  }
}
